MANIFEST.in
README.md
git-icdiff
icdiff.py
setup.py
icdiff.egg-info/PKG-INFO
icdiff.egg-info/SOURCES.txt
icdiff.egg-info/dependency_links.txt
icdiff.egg-info/entry_points.txt
icdiff.egg-info/top_level.txt