Metadata-Version: 1.0
Name: icdiff
Version: 2.0.5
Summary: improved colored diff
Home-page: http://www.jefftk.com/icdiff
Author: Jeff Kaufman
Author-email: jeff@jefftk.com
License: UNKNOWN
Platform: UNKNOWN
